overpass/__init__.py
overpass/api.py
overpass/errors.py
overpass/queries.py
overpass/utils.py
overpass2-0.6.3.dist-info/LICENSE.txt
overpass2-0.6.3.dist-info/METADATA
overpass2-0.6.3.dist-info/WHEEL
overpass2-0.6.3.dist-info/top_level.txt
overpass2-0.6.3.dist-info/RECORD
